README.md
setup.py
api/__init__.py
gfl/__init__.py
gfl.egg-info/PKG-INFO
gfl.egg-info/SOURCES.txt
gfl.egg-info/dependency_links.txt
gfl.egg-info/top_level.txt
gfl.egg-info/zip-safe
gfl/core/__init__.py
gfl/core/aggregator.py
gfl/core/client.py
gfl/core/communicate_client.py
gfl/core/communicate_server.py
gfl/core/job_manager.py
gfl/core/server.py
gfl/core/strategy.py
gfl/core/trainer.py
gfl/core/trainer_controller.py
gfl/entity/__init__.py
gfl/entity/job.py
gfl/entity/model.py
gfl/entity/runtime_config.py
gfl/exceptions/__init__.py
gfl/exceptions/fl_expection.py
gfl/lib/__init__.py
gfl/utils/__init__.py
gfl/utils/utils.py
test/__init__.py
test/test_web3.py